[{"id":1,"first_name":"Auroora","age":1},
{"id":2,"first_name":"Francisco","age":2},
{"id":3,"first_name":"Eldridge","age":3},
{"id":4,"first_name":"Liam","age":4},
{"id":5,"first_name":"Gino","age":5},
{"id":6,"first_name":"Ximenez","age":6},
{"id":7,"first_name":"Norine","age":7},
{"id":8,"first_name":"Roxana","age":8},
{"id":9,"first_name":"Alex","age":9},
{"id":10,"first_name":"Crichton","age":10},
{"id":11,"first_name":"Dalton","age":11},
{"id":12,"first_name":"Cassaundra","age":12},
{"id":13,"first_name":"Gisella","age":13},
{"id":14,"first_name":"Karissa","age":14},
{"id":15,"first_name":"Lorena","age":15},
{"id":16,"first_name":"Farrel","age":16},
{"id":17,"first_name":"Sebastian","age":17},
{"id":18,"first_name":"Sheilakathryn","age":18},
{"id":19,"first_name":"Bliss","age":19},
{"id":20,"first_name":"James","age":20},
{"id":21,"first_name":"Gwen","age":21},
{"id":22,"first_name":"Neddie","age":22},
{"id":23,"first_name":"Nels","age":23},
{"id":24,"first_name":"Lillis","age":24},
{"id":25,"first_name":"Corty","age":25},
{"id":26,"first_name":"Wanids","age":26},
{"id":27,"first_name":"Tony","age":27},
{"id":28,"first_name":"Dean","age":28},
{"id":29,"first_name":"Trixy","age":29},
{"id":30,"first_name":"Gabby","age":30},
{"id":31,"first_name":"Immanuel","age":31},
{"id":32,"first_name":"Vassili","age":32},
{"id":33,"first_name":"Esmaria","age":33},
{"id":34,"first_name":"Rhett","age":34},
{"id":35,"first_name":"Betsy","age":35},
{"id":36,"first_name":"Meridith","age":36},
{"id":37,"first_name":"Rozina","age":37},
{"id":38,"first_name":"Morgana","age":38},
{"id":39,"first_name":"Eddy","age":39},
{"id":40,"first_name":"Elliott","age":40},
{"id":41,"first_name":"Kalina","age":41},
{"id":42,"first_name":"Faythe","age":42},
{"id":43,"first_name":"Wynn","age":43},
{"id":44,"first_name":"West","age":44},
{"id":45,"first_name":"Wolfie","age":45},
{"id":46,"first_name":"Odelinda","age":46},
{"id":47,"first_name":"Wilbert","age":47},
{"id":48,"first_name":"Averill","age":48},
{"id":49,"first_name":"Demetre","age":49},
{"id":50,"first_name":"Benjie","age":50}]